LICENSE.txt
README.md
setup.py
regression_omari/__init__.py
regression_omari/regression.py
regression_omari.egg-info/PKG-INFO
regression_omari.egg-info/SOURCES.txt
regression_omari.egg-info/dependency_links.txt
regression_omari.egg-info/top_level.txt