Metadata-Version: 2.1
Name: regression_omari
Version: 0.1
Summary: A simple linear regression model implemented from scratch.
Home-page: https://github.com/yourusername/regression_pkg
Author: Your Name
Author-email: your.email@example.com
Classifier: Programming Language :: Python :: 3
Classifier: License :: OSI Approved :: MIT License
Classifier: Operating System :: OS Independent
Requires-Python: >=3.6
License-File: LICENSE.txt
